MANIFEST.in
README.md
setup.py
alipay/__init__.py
alipay/api.py
alipay/antom/__init__.py
alipay/antom/online.py
alipay/comm/__init__.py
alipay/comm/antom.py
alipay/comm/comm.py
alipay/data/methods.csv
alipay/koubei/__init__.py
alipay/koubei/kb.py
alipay/mybank/__init__.py
alipay/mybank/mybank.py
alipay/pay/__init__.py
alipay/pay/pay.py
alipay_sdk.egg-info/PKG-INFO
alipay_sdk.egg-info/SOURCES.txt
alipay_sdk.egg-info/dependency_links.txt
alipay_sdk.egg-info/requires.txt
alipay_sdk.egg-info/top_level.txt
alipay_sdk.egg-info/zip-safe
tests/__init__.py
tests/test_antom.py
tests/test_comm.py
tests/test_koubei.py
tests/test_pay.py