Metadata-Version: 2.1
Name: alipay-sdk
Version: 2.0.0
Summary: AliPay Python SDK
Home-page: https://github.com/block-cat/alipay_sdk
Author: blackcat
Author-email: kfx2007@163.com
License: GNU
Keywords: alipay sdk
Classifier: License :: OSI Approved :: GNU Affero General Public License v3
Classifier: Programming Language :: Python
Classifier: Operating System :: OS Independent
Classifier: Topic :: Scientific/Engineering :: Astronomy
Classifier: Topic :: Scientific/Engineering :: GIS
Classifier: Topic :: Scientific/Engineering :: Mathematics
Classifier: Intended Audience :: Science/Research
Classifier: Intended Audience :: Developers
Classifier: Intended Audience :: Information Technology
Requires-Dist: requests
Requires-Dist: pycryptodome
